cdk_backup_plan/__init__.py
cdk_backup_plan/py.typed
cdk_backup_plan/_jsii/__init__.py
cdk_backup_plan/_jsii/cdk-backup-plan@0.0.8.jsii.tgz
cdk_backup_plan-0.0.8.dist-info/LICENSE
cdk_backup_plan-0.0.8.dist-info/METADATA
cdk_backup_plan-0.0.8.dist-info/WHEEL
cdk_backup_plan-0.0.8.dist-info/top_level.txt
cdk_backup_plan-0.0.8.dist-info/RECORD
